pollbot/__init__.py
pollbot/__main__.py
pollbot/api.yaml
pollbot/app.py
pollbot/contribute.yaml
pollbot/exceptions.py
pollbot/middlewares.py
pollbot/utils.py
pollbot/tasks/__init__.py
pollbot/tasks/archives.py
pollbot/tasks/balrog.py
pollbot/tasks/bedrock.py
pollbot/tasks/bouncer.py
pollbot/tasks/buildhub.py
pollbot/tasks/crash_stats.py
pollbot/tasks/product_details.py
pollbot/tasks/telemetry.py
pollbot/views/__init__.py
pollbot/views/decorators.py
pollbot/views/home.py
pollbot/views/product.py
pollbot/views/release.py
pollbot/views/utilities.py
pollbot-1.1.4.dist-info/DESCRIPTION.rst
pollbot-1.1.4.dist-info/METADATA
pollbot-1.1.4.dist-info/RECORD
pollbot-1.1.4.dist-info/WHEEL
pollbot-1.1.4.dist-info/entry_points.txt
pollbot-1.1.4.dist-info/metadata.json
pollbot-1.1.4.dist-info/top_level.txt
