Metadata-Version: 2.0
Name: pollbot
Version: 1.1.4
Summary: A service that polls other services about releases deliveries.
Home-page: https://github.com/mozilla/PollBot
Author: Mozilla Services
Author-email: storage-team@mozilla.com
License: Mozilla Public License 2.0
Keywords: web sync json storage services
Platform: UNKNOWN
Classifier: Programming Language :: Python
Classifier: Programming Language :: Python :: 3
Classifier: Programming Language :: Python :: 3.6
Classifier: Programming Language :: Python :: Implementation :: CPython
Classifier: Topic :: Internet :: WWW/HTTP
Classifier: Topic :: Internet :: WWW/HTTP :: WSGI :: Application
Classifier: License :: OSI Approved :: Mozilla Public License 2.0 (MPL 2.0)
Requires-Dist: aiohttp (<3)
Requires-Dist: aiohttp-cors
Requires-Dist: aiohttp-swagger
Requires-Dist: ruamel.yaml
Requires-Dist: pyquery
